mozlogging/__init__.py
mozlogging/formatters.py
mozlogging-0.1.0.dist-info/DESCRIPTION.rst
mozlogging-0.1.0.dist-info/METADATA
mozlogging-0.1.0.dist-info/RECORD
mozlogging-0.1.0.dist-info/WHEEL
mozlogging-0.1.0.dist-info/metadata.json
mozlogging-0.1.0.dist-info/top_level.txt
