Metadata-Version: 2.0
Name: mozlogging
Version: 0.1.0
Summary: MozLog with the logging Module
Home-page: https://github.com/smacleod/mozlogging
Author: Steven MacLeod
Author-email: smacleod@mozilla.com
License: MPL 2.0
Platform: UNKNOWN
Classifier: Development Status :: 3 - Alpha
Classifier: Intended Audience :: Developers
Classifier: Topic :: Software Development :: Build Tools
Classifier: License :: OSI Approved :: Mozilla Public License 2.0 (MPL 2.0)
Classifier: Programming Language :: Python
Classifier: Programming Language :: Python :: 3
Classifier: Programming Language :: Python :: 3.5
